csv_parser_utils/__init__.py
csv_parser_utils/main.py
csv_parser_utils-0.0.1.dist-info/licenses/LICENSE
csv_parser_utils-0.0.1.dist-info/METADATA
csv_parser_utils-0.0.1.dist-info/WHEEL
csv_parser_utils-0.0.1.dist-info/top_level.txt
csv_parser_utils-0.0.1.dist-info/RECORD
