Metadata-Version: 2.4
Name: csv-parser-utils
Version: 0.0.1
Summary: Um pacote para manipular dados de arquivos CSV, usando pandas.
Home-page: https://github.com/gallothiago/csv-parser-utils
Author: Thiago Gallo
Author-email: gallothiago2013@gmail.com
Classifier: Programming Language :: Python :: 3
Classifier: License :: OSI Approved :: MIT License
Classifier: Operating System :: OS Independent
Requires-Python: >=3.7
License-File: LICENSE
Requires-Dist: pandas
Requires-Dist: seaborn
Dynamic: author
Dynamic: author-email
Dynamic: classifier
Dynamic: description
Dynamic: description-content-type
Dynamic: home-page
Dynamic: license-file
Dynamic: requires-dist
Dynamic: requires-python
Dynamic: summary
